CHANGELOG.md
src/__init__.py
src/cli.py
src/data/__init__.py
src/data/components/__init__.py
src/data/mnist_datamodule.py
src/eval.py
src/models/__init__.py
src/models/components/__init__.py
src/models/components/simple_dense_net.py
src/models/mnist_module.py
src/train.py
src/utils/__init__.py
src/utils/instantiators.py
src/utils/logging_utils.py
src/utils/pylogger.py
src/utils/rich_utils.py
src/utils/utils.py
pansharpening-0.1.0.dist-info/METADATA
pansharpening-0.1.0.dist-info/WHEEL
pansharpening-0.1.0.dist-info/entry_points.txt
pansharpening-0.1.0.dist-info/RECORD
