Metadata-Version: 2.1
Name: pansharpening
Version: 0.1.0
Summary: Deep learning for pansharpening in remote sensing
Home-page: https://XavierJiezou.github.io/Pansharpening
License: MIT
Keywords: deep learning,remote sensing,pansharpening
Author: XavierJiezou
Author-email: 878972272@qq.com
Requires-Python: >=3.8.1,<4.0.0
Classifier: License :: OSI Approved :: MIT License
Classifier: Programming Language :: Python :: 3
Classifier: Programming Language :: Python :: 3.9
Classifier: Programming Language :: Python :: 3.10
Classifier: Programming Language :: Python :: 3.11
Classifier: Topic :: Software Development :: Libraries :: Python Modules
Requires-Dist: fire (>=0.5.0,<0.6.0)
Requires-Dist: hydra-colorlog (>=1.2.0,<2.0.0)
Requires-Dist: hydra-core (>=1.3.2,<2.0.0)
Requires-Dist: hydra-optuna-sweeper (>=1.2.0,<2.0.0)
Requires-Dist: lightning (>=2.0.0,<3.0.0)
Requires-Dist: rich (>=13.6.0,<14.0.0)
Requires-Dist: torch (>=2.1.0,<3.0.0)
Requires-Dist: torchmetrics (>=0.11.4,<0.12.0)
Requires-Dist: torchvision (>=0.16.0,<0.17.0)
Project-URL: Documentation, https://pansharpening.readthedocs.io
Project-URL: Repository, https://github.com/XavierJiezou/Pansharpening
